pytrading_toolkit/__init__.py
pytrading_toolkit/config/__init__.py
pytrading_toolkit/config/base.py
pytrading_toolkit/config/master_config_loader.py
pytrading_toolkit/config/exchange/__init__.py
pytrading_toolkit/config/exchange/bybit.py
pytrading_toolkit/config/exchange/upbit.py
pytrading_toolkit/core/auto_recovery.py
pytrading_toolkit/core/dashboard.py
pytrading_toolkit/core/system_manager.py
pytrading_toolkit/health/__init__.py
pytrading_toolkit/health/maintenance_detector.py
pytrading_toolkit/health/monitor.py
pytrading_toolkit/health/simple_detector.py
pytrading_toolkit/indicators/__init__.py
pytrading_toolkit/indicators/manager.py
pytrading_toolkit/indicators/talib_manager.py
pytrading_toolkit/logging/__init__.py
pytrading_toolkit/logging/setup.py
pytrading_toolkit/notifications/__init__.py
pytrading_toolkit/notifications/telegram.py
pytrading_toolkit/security/access_control.py
pytrading_toolkit/security/audit_logger.py
pytrading_toolkit/security/encryption.py
pytrading_toolkit/tools/config_base.py
pytrading_toolkit/tools/config_setup.py
pytrading_toolkit/tools/config_wizard.py
pytrading_toolkit/tools/emergency_log_extractor.py
pytrading_toolkit/tools/indicator_manager.py
pytrading_toolkit/tools/logger_setup.py
pytrading_toolkit/tools/multi_instance_manager.py
pytrading_toolkit/tools/telegram_notifier.py
pytrading_toolkit/tools/unified_config.py
pytrading_toolkit/tools/user_config.py
pytrading_toolkit/tools/utils.py
pytrading_toolkit/trading/__init__.py
pytrading_toolkit/trading/bybit_data_manager.py
pytrading_toolkit/trading/bybit_trader.py
pytrading_toolkit/trading/position_manager.py
pytrading_toolkit/utils/__init__.py
pytrading_toolkit/utils/advanced_logger.py
pytrading_toolkit/utils/async_manager.py
pytrading_toolkit/utils/cache_manager.py
pytrading_toolkit/utils/connection_manager.py
pytrading_toolkit/utils/data_utils.py
pytrading_toolkit/utils/data_validator.py
pytrading_toolkit/utils/error_handler.py
pytrading_toolkit/utils/log_analyzer.py
pytrading_toolkit-1.1.0.dist-info/licenses/LICENSE
pytrading_toolkit-1.1.0.dist-info/METADATA
pytrading_toolkit-1.1.0.dist-info/WHEEL
pytrading_toolkit-1.1.0.dist-info/top_level.txt
pytrading_toolkit-1.1.0.dist-info/RECORD
