Metadata-Version: 2.4
Name: pytrading-toolkit
Version: 1.1.0
Summary: Python 암호화폐 트레이딩 봇 개발 툴킷
Home-page: https://pypi.org/project/pytrading-toolkit/
Author: SHY
Author-email: Crypto Auto Trader Team <your-email@example.com>
License-Expression: MIT
Project-URL: Homepage, https://github.com/your-username/pytrading-toolkit
Project-URL: Bug Reports, https://github.com/your-username/pytrading-toolkit/issues
Project-URL: Source, https://github.com/your-username/pytrading-toolkit
Project-URL: Documentation, https://pytrading-toolkit.readthedocs.io/
Keywords: trading,crypto,cryptocurrency,bitcoin,indicators,telegram,bot,toolkit,python
Classifier: Development Status :: 3 - Alpha
Classifier: Intended Audience :: Developers
Classifier: Intended Audience :: Financial and Insurance Industry
Classifier: Topic :: Office/Business :: Financial :: Investment
Classifier: Topic :: Software Development :: Libraries :: Python Modules
Classifier: Programming Language :: Python :: 3
Classifier: Programming Language :: Python :: 3.8
Classifier: Programming Language :: Python :: 3.9
Classifier: Programming Language :: Python :: 3.10
Classifier: Programming Language :: Python :: 3.11
Classifier: Programming Language :: Python :: 3.12
Classifier: Operating System :: OS Independent
Requires-Python: >=3.8
License-File: LICENSE
Requires-Dist: ta>=0.10.2
Requires-Dist: python-telegram-bot>=20.7
Requires-Dist: psutil>=5.9.0
Requires-Dist: pyyaml>=6.0
Requires-Dist: requests>=2.28.0
Provides-Extra: dev
Requires-Dist: pytest>=7.0.0; extra == "dev"
Requires-Dist: pytest-cov>=4.0.0; extra == "dev"
Requires-Dist: black>=22.0.0; extra == "dev"
Requires-Dist: flake8>=4.0.0; extra == "dev"
Requires-Dist: mypy>=0.950; extra == "dev"
Provides-Extra: telegram
Requires-Dist: python-telegram-bot>=20.0; extra == "telegram"
Provides-Extra: analysis
Requires-Dist: matplotlib>=3.5.0; extra == "analysis"
Requires-Dist: plotly>=5.0.0; extra == "analysis"
Requires-Dist: jupyter>=1.0.0; extra == "analysis"
Dynamic: author
Dynamic: home-page
Dynamic: license-file
Dynamic: requires-python
